myanmar_words/__init__.py
myanmar_words/main.py
myanmar_words/data/adjectives.json
myanmar_words/data/adverbs.json
myanmar_words/data/all.json
myanmar_words/data/conjunctions.json
myanmar_words/data/nouns.json
myanmar_words/data/particles.json
myanmar_words/data/postpositions.json
myanmar_words/data/pronouns.json
myanmar_words/data/verbs.json
myanmar_words-1.0.2.dist-info/LICENCE
myanmar_words-1.0.2.dist-info/METADATA
myanmar_words-1.0.2.dist-info/WHEEL
myanmar_words-1.0.2.dist-info/top_level.txt
myanmar_words-1.0.2.dist-info/RECORD
