Metadata-Version: 2.1
Name: myanmar_words
Version: 1.0.2
Summary: A Python library for working with Myanmar words and sentences.
Home-page: https://github.com/linhtutkyawdev/myanmar_words
Author: Lin Htut Kyaw
Author-email: linhtutkyaw.dev@gmail.com
License: MIT
Classifier: Programming Language :: Python :: 3
Classifier: License :: OSI Approved :: MIT License
Classifier: Operating System :: OS Independent
Requires-Python: >=3.6
License-File: LICENCE
